Metadata-Version: 1.0
Name: katuula-probability
Version: 1.0
Summary: Gaussian and binomail distributions
Home-page: UNKNOWN
Author: Katuula Joel
Author-email: katuula@gmail.com
License: UNKNOWN
Platform: UNKNOWN
